{
  "save_path": "models/saved/pinn",
  "config_path": "config/simple_hjb_config.json",
  "device": "cuda",
  "train": true,
  "load_if_exists": true,
  "best": false,
  "verbose": true,
  "plot": true,
  "plot_loss": true,
  "save": ["best", "every"],
  "save_n": 50,
  "architecture": "FC",
  "activation": "ReLU",
  "epochs": 1000,
  "lr": 1e-3,
  "adaptive": true,
  "lr_factor": 0.90,
  "lr_patience": 20,
  "n_paths": 1024,
  "batch_size": 1024,
  "n_pinn": 256,
  "n_simulations": 3,
  "lambda_Y": 1,
  "lambda_T": 0.1,
  "lambda_TG": 0.01,
  "lambda_pinn": 0
}