{
  "device": "cuda",
  "parallel": false,
  "epochs": 100000,
  "K": 50,
  "batch_size": 1024,
  "rescale_y0": true,
  "input_bn": false,
  "affine": false,
  "strong_grad_output": false,
  "scale_output": 100.0,
  "network_type": "dY",
  "supervised": false,
  "architecture": "lstmwithsubnets",
  "activation": "GELU",
  "Y0_layers": [128, 128],
  "Y_layers": [128, 128],
  "subnet_type": "naisnet",
  "lstm_layers": [32, 32],
  "lstm_type": "naislstm",
  "adaptive": true,
  "adaptive_factor": 0.95,
  "lr": 1e-2,
  "adaptive_loss": true,
  "lambda_Y0": 1,
  "lambda_Y": 1,
  "lambda_dY": 0,
  "lambda_dYt": 0,
  "lambda_T": 1,
  "lambda_TG": 1,
  "lambda_pinn": 1,
  "lambda_reg": 0,
  "lambda_cost": 1,
  "sobol_points": false,
  "use_linear_approx": false,
  "loss_threshold": 1000.0,
  "second_order_taylor": true,
  "train": true,
  "load_if_exists": true,
  "resume": true,
  "save_dir": "saved_models/aid",
  "dynamics_path": "config/dynamics_configs/aid_config.json",
  "save": ["best", "every"],
  "save_n": 50,
  "plot_n": 100,
  "best": true,
  "verbose": true,
  "plot": false,
  "plot_loss": false,
  "n_simulations": 5
}